ai_chat_kit/__init__.py
ai_chat_kit/adapters/__init__.py
ai_chat_kit/adapters/fastapi/__init__.py
ai_chat_kit/adapters/fastapi/main.py
ai_chat_kit/adapters/fastapi/providers.py
ai_chat_kit/adapters/fastapi/sqlite_memory.py
ai_chat_kit-0.1.0.dist-info/METADATA
ai_chat_kit-0.1.0.dist-info/WHEEL
ai_chat_kit-0.1.0.dist-info/top_level.txt
ai_chat_kit-0.1.0.dist-info/RECORD
