Metadata-Version: 2.4
Name: ai-chat-kit
Version: 0.1.0
Summary: ai-chat-kit Python adapters (FastAPI) for streaming chat
Author: Shrikant Jagtap
License: MIT
Keywords: ai,chat,fastapi,sse,streaming
Classifier: Development Status :: 3 - Alpha
Classifier: Intended Audience :: Developers
Classifier: License :: OSI Approved :: MIT License
Classifier: Programming Language :: Python :: 3
Classifier: Programming Language :: Python :: 3 :: Only
Classifier: Programming Language :: Python :: 3.10
Classifier: Programming Language :: Python :: 3.11
Classifier: Programming Language :: Python :: 3.12
Classifier: Framework :: FastAPI
Classifier: Topic :: Software Development :: Libraries
Requires-Python: >=3.10
Requires-Dist: fastapi>=0.110.0
Requires-Dist: uvicorn[standard]>=0.23.0
Requires-Dist: httpx>=0.27.0
